{
  "main": {
    "id": "a1b2a353fdef6541",
    "type": "split",
    "children": [
      {
        "id": "d4ab09fa704539ed",
        "type": "tabs",
        "children": [
          {
            "id": "8fa575f8cc41f267",
            "type": "leaf",
            "state": {
              "type": "markdown",
              "state": {
                "file": "retos-pico/Web/SQL Direct.md",
                "mode": "source",
                "source": false
              }
            }
          }
        ]
      }
    ],
    "direction": "vertical"
  },
  "left": {
    "id": "dd78114d16273e77",
    "type": "split",
    "children": [
      {
        "id": "917524d5dc23ab39",
        "type": "tabs",
        "children": [
          {
            "id": "0f6b864a85aa9c15",
            "type": "leaf",
            "state": {
              "type": "file-explorer",
              "state": {
                "sortOrder": "alphabetical"
              }
            }
          },
          {
            "id": "dc18195db0f0628e",
            "type": "leaf",
            "state": {
              "type": "search",
              "state": {
                "query": "",
                "matchingCase": false,
                "explainSearch": false,
                "collapseAll": false,
                "extraContext": false,
                "sortOrder": "alphabetical"
              }
            }
          },
          {
            "id": "2900ccde61990429",
            "type": "leaf",
            "state": {
              "type": "bookmarks",
              "state": {}
            }
          }
        ]
      }
    ],
    "direction": "horizontal",
    "width": 263.5
  },
  "right": {
    "id": "f65268e36e237ca4",
    "type": "split",
    "children": [
      {
        "id": "6935952109b55eee",
        "type": "tabs",
        "children": [
          {
            "id": "072a5fdcbe3d9a83",
            "type": "leaf",
            "state": {
              "type": "backlink",
              "state": {
                "file": "retos-pico/Web/SQL Direct.md",
                "collapseAll": false,
                "extraContext": false,
                "sortOrder": "alphabetical",
                "showSearch": false,
                "searchQuery": "",
                "backlinkCollapsed": false,
                "unlinkedCollapsed": true
              }
            }
          },
          {
            "id": "0bef48e89a05a75f",
            "type": "leaf",
            "state": {
              "type": "outgoing-link",
              "state": {
                "file": "retos-pico/Web/SQL Direct.md",
                "linksCollapsed": false,
                "unlinkedCollapsed": true
              }
            }
          },
          {
            "id": "1fe6957232c453e8",
            "type": "leaf",
            "state": {
              "type": "tag",
              "state": {
                "sortOrder": "frequency",
                "useHierarchy": true
              }
            }
          },
          {
            "id": "8d39988f45d39abb",
            "type": "leaf",
            "state": {
              "type": "outline",
              "state": {
                "file": "retos-pico/Web/SQL Direct.md"
              }
            }
          },
          {
            "id": "f036a1f2511fa59e",
            "type": "leaf",
            "state": {
              "type": "all-properties",
              "state": {
                "sortOrder": "frequency"
              }
            }
          }
        ],
        "currentTab": 2
      }
    ],
    "direction": "horizontal",
    "width": 200
  },
  "left-ribbon": {
    "hiddenItems": {
      "switcher:Abrir selector rápido": false,
      "graph:Abrir vista gráfica": false,
      "canvas:Crear nuevo canvas": false,
      "daily-notes:Abrir la nota de hoy": false,
      "templates:Insertar plantilla": false,
      "command-palette:Abrir paleta de comandos": false,
      "workspaces:Gestionar disposiciones de espacio de trabajo": false,
      "audio-recorder:Empezar/Parar de grabar": false
    }
  },
  "active": "8fa575f8cc41f267",
  "lastOpenFiles": [
    "retos-pico/Web/Search source.md",
    "retos-pico/Web/SQL Direct.md",
    "retos-pico/Web/Power Cookie.md",
    "Pasted image 20231024153140.png",
    "Pasted image 20231024153122.png",
    "retos-pico/Web/Secrets.md",
    "Pasted image 20231024152622.png",
    "Pasted image 20231024152532.png",
    "Pasted image 20231024152245.png",
    "Pasted image 20231024151236.png",
    "retos-pico/Web/Roboto Sans.md",
    "Pasted image 20231024005113.png",
    "Pasted image 20231024004648.png",
    "retos-pico/Web/Forbidden Paths.md",
    "Pasted image 20231024002347.png",
    "retos-pico/Forense/St3g0.md",
    "retos-pico/Web/Local Authority.md",
    "retos-pico/Web/Includes.md",
    "retos-pico/Web/Inspect HTML.md",
    "Pasted image 20231024000431.png",
    "retos-pico/Forense/Wireshark doo dooo do doo....md",
    "retos-pico/Forense/information.md",
    "retos-pico/Forense/Redaction gone wrong.md",
    "retos-pico/Forense/Packets Primer.md",
    "retos-pico/Forense/Lookey here.md",
    "Plantillas/Plantilla.md",
    "retos-pico/Web/web3/Cookies.md",
    "retos-pico/Forense/Matryoshka doll.md",
    "Plantillas",
    "retos-bandit/Bandit Level 33→ Level 34.md",
    "retos-pico/Forense/Enhance!.md",
    "retos-bandit/Bandit Level 3 → Level 4.md",
    "retos-pico/Parte 2/2-Bases.md",
    "retos-pico/General Skllls/Serpentine.md",
    "retos-pico/General Skllls/PW Crack 5.md",
    "retos-pico/General Skllls/HashingJobApp.md",
    "retos-pico/General Skllls/First Find.md",
    "Recording 20231018223832.webm",
    "Recording 20231018223734.webm",
    "Recording 20231018224210.webm",
    "Recording 20231018224136.webm",
    "Recording 20231018224113.webm",
    "Recording 20231018223745.webm",
    "Recording 20231018223228.webm",
    "Recording 20231018223111.webm",
    "Sin título.canvas",
    "kali.pdf"
  ]
}